[
  {
    "rank": 1,
    "name": "יעקב",
    "score": 67
  },
  {
    "rank": 2,
    "name": "אפרת",
    "score": 65
  },
  {
    "rank": 3,
    "name": "דן",
    "score": 63
  },
  {
    "rank": "-",
    "name": "מאור רובינוב",
    "score": 63
  },
  {
    "rank": 5,
    "name": "אוהד",
    "score": 62
  },
  {
    "rank": 6,
    "name": "אכ\"ש",
    "score": 60
  },
  {
    "rank": "-",
    "name": "ליהי",
    "score": 60
  },
  {
    "rank": 8,
    "name": "דמיאן",
    "score": 59
  },
  {
    "rank": 9,
    "name": "שרון",
    "score": 57
  },
  {
    "rank": "-",
    "name": "מאור בין",
    "score": 57
  },
  {
    "rank": 11,
    "name": "ייטב",
    "score": 56
  },
  {
    "rank": 12,
    "name": "ניר ונטע",
    "score": 55
  },
  {
    "rank": 13,
    "name": "ברוש",
    "score": 54
  },
  {
    "rank": 14,
    "name": "יובל",
    "score": 53
  },
  {
    "rank": "-",
    "name": "אלעד",
    "score": 53
  },
  {
    "rank": "-",
    "name": "קזז",
    "score": 53
  },
  {
    "rank": 17,
    "name": "אייל",
    "score": 47
  },
  {
    "rank": 18,
    "name": "יותם",
    "score": 43
  }
]
